pybreaks/__init__.py
pybreaks/adjust_freq_quantile_matching.py
pybreaks/adjust_higher_order_moments.py
pybreaks/adjust_linear_model_pair_fitting.py
pybreaks/base.py
pybreaks/break_adjust.py
pybreaks/break_adjust_check.py
pybreaks/break_detect.py
pybreaks/break_multi.py
pybreaks/break_test.py
pybreaks/fligner.py
pybreaks/horizontal_errors.py
pybreaks/lmoments_ks.py
pybreaks/model_lin_regress.py
pybreaks/model_poly_regress.py
pybreaks/temp_coverage.py
pybreaks/timeframes.py
pybreaks/utils.py
pybreaks-0.4.dist-info/licenses/AUTHORS.rst
pybreaks-0.4.dist-info/licenses/LICENSE.txt
pybreaks-0.4.dist-info/METADATA
pybreaks-0.4.dist-info/WHEEL
pybreaks-0.4.dist-info/top_level.txt
pybreaks-0.4.dist-info/RECORD
