Metadata-Version: 2.4
Name: pybreaks
Version: 0.4
Summary: Temporal break correction as used in the ESA CCI SM processor
Author-email: TU Wien <wolfgang.preimesberger@geo.tuwien.ac.at>
License: mit
Project-URL: Homepage, https://github.com/TUW-GEO/pybreaks/
Project-URL: Documentation, https://pybreaks.readthedocs.io/en/latest/
Classifier: Development Status :: 4 - Beta
Classifier: Programming Language :: Python
Requires-Python: >=3.6
License-File: LICENSE.txt
License-File: AUTHORS.rst
Requires-Dist: importlib-metadata; python_version < "3.8"
Requires-Dist: numpy
Requires-Dist: netCDF4
Requires-Dist: scipy
Requires-Dist: pandas
Requires-Dist: pyproj
Requires-Dist: pykdtree
Requires-Dist: scikit-learn
Requires-Dist: statsmodels
Requires-Dist: datetime
Requires-Dist: matplotlib
Requires-Dist: seaborn
Requires-Dist: smecv_grid
Requires-Dist: pytesmo
Requires-Dist: more_itertools
Requires-Dist: lmoments3
Provides-Extra: testing
Requires-Dist: pytest-cov; extra == "testing"
Requires-Dist: coverage; extra == "testing"
Requires-Dist: pytest; extra == "testing"
Provides-Extra: building
Requires-Dist: setuptools>=46.1.0; extra == "building"
Requires-Dist: setuptools_scm[toml]>=5; extra == "building"
Requires-Dist: wheel; extra == "building"
Requires-Dist: packaging; extra == "building"
Requires-Dist: build; extra == "building"
Requires-Dist: twine; extra == "building"
Provides-Extra: docs
Requires-Dist: sphinx<7,>=3.2.1; extra == "docs"
Requires-Dist: sphinx_rtd_theme; extra == "docs"
Requires-Dist: mock; extra == "docs"
Requires-Dist: pillow; extra == "docs"
Requires-Dist: recommonmark; extra == "docs"
Requires-Dist: readthedocs-sphinx-ext; extra == "docs"
Requires-Dist: myst_parser; extra == "docs"
Requires-Dist: nbsphinx; extra == "docs"
Dynamic: license-file
